mssfp/__about__.py
mssfp/__init__.py
mssfp/plots.py
mssfp/run.py
mssfp/phantoms/__init__.py
mssfp/phantoms/brain.py
mssfp/phantoms/fieldmap.py
mssfp/phantoms/noise.py
mssfp/phantoms/phantom.py
mssfp/phantoms/shepp_logan.py
mssfp/phantoms/simple.py
mssfp/recons/__init__.py
mssfp/recons/fft.py
mssfp/recons/gs_recon.py
mssfp/recons/planet.py
mssfp/recons/rsos.py
mssfp/recons/super_fov.py
mssfp/simulations/__init__.py
mssfp/simulations/ssfp.py
mssfp-0.0.14.dist-info/METADATA
mssfp-0.0.14.dist-info/WHEEL
mssfp-0.0.14.dist-info/RECORD
