Metadata-Version: 2.4
Name: mssfp
Version: 0.0.14
Summary: mSSFP is library for image reconstuction for multi-acqusition SSFP
Project-URL: Homepage, https://github.com/michaelmendoza/mssfp
Project-URL: Bug Tracker, https://github.com/michaelmendoza/mssfp/issues
Author-email: Michael Mendoza <askmichaelmendoza@gmail.com>
License-Expression: MIT
Keywords: grappa,mri,sense
Classifier: Programming Language :: Python :: 3
Requires-Python: >=3.8
Requires-Dist: elasticdeform
Requires-Dist: ellipsinator
Requires-Dist: gdown
Requires-Dist: imageio
Requires-Dist: imageio-ffmpeg
Requires-Dist: jupyterlab
Requires-Dist: matplotlib
Requires-Dist: nibabel
Requires-Dist: numpy
Requires-Dist: scikit-image
Requires-Dist: scipy
Requires-Dist: tqdm
Provides-Extra: examples
Requires-Dist: jupyterlab; extra == 'examples'
Requires-Dist: matplotlib; extra == 'examples'
